datamonk/prefect_tasks/__init__.py
datamonk/prefect_tasks/general.py
datamonk/prefect_tasks/invest.py
datamonk_prefect_tasks-0.1.5.dist-info/WHEEL
datamonk_prefect_tasks-0.1.5.dist-info/METADATA
datamonk_prefect_tasks-0.1.5.dist-info/RECORD
